{"id":"48875298","premium":false,"billing_type":{"id":"standard","name":"Стандарт"},"relations":[],"name":"Python developer (проект)","insider_interview":null,"response_letter_required":false,"area":{"id":"1","name":"Москва","url":"https://api.hh.ru/areas/1?host=hh.ru"},"salary":{"from":3000,"to":null,"currency":"USD","gross":false},"type":{"id":"open","name":"Открытая"},"address":null,"allow_messages":true,"site":{"id":"hh","name":"hh.ru"},"experience":{"id":"between1And3","name":"От 1 года до 3 лет"},"schedule":{"id":"remote","name":"Удаленная работа"},"employment":{"id":"project","name":"Проектная работа"},"department":null,"contacts":null,"description":"<p>Мы делаем ML-приложение, которое изучает поведение пользователей мобильных игр, определяя их текущие потребности, чтобы персонализировать предложения о покупке игровой валюты или любых покупок в приложении.</p> <p>На основе этого анализа строятся гипотезы о выборе наиболее конверсионных вариантов офферов для каждого пользователя. Таким образом мы помогаем владельцам игр и издателям увеличивать свой LTV и зарабатывать больше.</p> <p><strong>Обязанности:</strong></p> <ul> <li>Написанием API для интеграции с клиентскими игровыми приложениями;</li> <li>Подготовкой А/Б тестов на основе обработанных ранее больших данных;</li> </ul> <p><strong>Требования:</strong></p> <ul> <li>Коммерческий опыт применения Python от 3-х лет;</li> <li>Опыт работы с:</li> </ul> <ol> <li>Любой СУБД - PostgreSQL, Oracle, MySql, MSSQL</li> <li>Python 3.x</li> <li>Asyncio</li> <li>Docker</li> <li>GitLab CI/CD</li> <li>Git</li> </ol> <ul> <li>Понимание в чем отличие Python фреймворков: Flask, Django, FastAPI, aiohttp, Sanic;</li> <li>Любовь к написанию Unit тестов;</li> </ul> <strong>Условия:</strong> <ul> <li>Оформление по ГПХ, самозанятость, ИП;</li> <li>Удаленная работа;</li> <li>Занятость на проекте - полгода с возможностью продления;</li> <li>От 3000$. </li> </ul>","branded_description":null,"vacancy_constructor_template":null,"key_skills":[],"accept_handicapped":false,"accept_kids":false,"archived":false,"response_url":null,"specializations":[{"id":"1.203","name":"Передача данных и доступ в интернет","profarea_id":"1","profarea_name":"Информационные технологии, интернет, телеком"},{"id":"1.475","name":"Игровое ПО","profarea_id":"1","profarea_name":"Информационные технологии, интернет, телеком"},{"id":"1.221","name":"Программирование, Разработка","profarea_id":"1","profarea_name":"Информационные технологии, интернет, телеком"},{"id":"1.9","name":"Web инженер","profarea_id":"1","profarea_name":"Информационные технологии, интернет, телеком"},{"id":"1.474","name":"Стартапы","profarea_id":"1","profarea_name":"Информационные технологии, интернет, телеком"}],"professional_roles":[{"id":"96","name":"Программист, разработчик"}],"code":null,"hidden":false,"quick_responses_allowed":false,"driver_license_types":[],"accept_incomplete_resumes":false,"employer":{"id":"5008916","name":"Грин Грей Софтворкс","url":"https://api.hh.ru/employers/5008916?host=hh.ru","alternate_url":"https://hh.ru/employer/5008916","logo_urls":{"original":"https://hhcdn.ru/employer-logo-original/825339.jpg","90":"https://hhcdn.ru/employer-logo/3742243.jpeg","240":"https://hhcdn.ru/employer-logo/3742244.jpeg"},"vacancies_url":"https://api.hh.ru/vacancies?employer_id=5008916&host=hh.ru","trusted":true},"published_at":"2021-11-23T12:08:40+0300","created_at":"2021-11-23T12:08:40+0300","negotiations_url":null,"suitable_resumes_url":null,"apply_alternate_url":"https://hh.ru/applicant/vacancy_response?vacancyId=48875298","has_test":false,"test":null,"alternate_url":"https://hh.ru/vacancy/48875298","working_days":[],"working_time_intervals":[],"working_time_modes":[],"accept_temporary":true}